README.md
setup.py
pydota2/__init__.py
pydota2.egg-info/PKG-INFO
pydota2.egg-info/SOURCES.txt
pydota2.egg-info/dependency_links.txt
pydota2.egg-info/top_level.txt